idemptx/__init__.py
idemptx/backend/__init__.py
idemptx/backend/base.py
idemptx/backend/memory.py
idemptx/backend/redis.py
idemptx/decorator.py
idemptx/exceptions.py
idemptx_redis6-0.2.3.dist-info/METADATA
idemptx_redis6-0.2.3.dist-info/WHEEL
idemptx_redis6-0.2.3.dist-info/licenses/LICENSE
idemptx_redis6-0.2.3.dist-info/RECORD
