Metadata-Version: 2.4
Name: idemptx-redis6
Version: 0.2.3
Summary: Idempotency decorator for FastAPI
License: MIT
License-File: LICENSE
Keywords: fastapi,idempotency,decorator,redis,cache
Author: OSpoon
Author-email: zxin088@gmail.com
Requires-Python: >=3.9,<4.0
Classifier: License :: OSI Approved :: MIT License
Classifier: Programming Language :: Python :: 3
Classifier: Programming Language :: Python :: 3.9
Classifier: Programming Language :: Python :: 3.10
Classifier: Programming Language :: Python :: 3.11
Classifier: Programming Language :: Python :: 3.12
Classifier: Programming Language :: Python :: 3.13
Classifier: Programming Language :: Python :: 3.14
Requires-Dist: fastapi
Requires-Dist: pydantic (>=2.0,<3.0)
Requires-Dist: redis (>=6.0,<7.0)
Project-URL: Documentation, https://github.com/OSpoon/idemptx#readme
Project-URL: Homepage, https://github.com/OSpoon/idemptx
Project-URL: Repository, https://github.com/OSpoon/idemptx
